manifest/__init__.py
manifest/base.py
manifest/instantiable.py
manifest/parse.py
manifest/py.typed
manifest/pydantic.py
manifest/utils.py
manifest/hooks/__init__.py
manifest/hooks/builtin.py
manifest/hooks/interface.py
manifest/hooks/expressions/__init__.py
manifest/hooks/expressions/operations.py
manifest/hooks/expressions/resolve.py
manifest/serializers/__init__.py
manifest/serializers/base.py
manifest/serializers/jsons.py
manifest/serializers/noop.py
manifest/serializers/tomls.py
manifest/serializers/yamls.py
python_manifest-2.3.3.dist-info/METADATA
python_manifest-2.3.3.dist-info/WHEEL
python_manifest-2.3.3.dist-info/licenses/LICENSE
python_manifest-2.3.3.dist-info/RECORD
