Metadata-Version: 2.4
Name: python-manifest
Version: 2.3.3
Summary: A modern toolkit for working with application manifests and configurations.
Project-URL: repository, https://github.com/emergentmethods/python-manifest
Author-email: Timothy Pogue <tim@emergentmethods.ai>
License: MIT
License-File: LICENSE
Requires-Python: <4.0,>=3.10
Requires-Dist: fsspec>=2024.10.0
Requires-Dist: pydantic<3.0,>=1.8
Requires-Dist: python-dotenv>=1.0.0
Requires-Dist: python-rapidjson>=1.10
Requires-Dist: pyyaml>=6.0
Requires-Dist: toml>=0.10.2
